funcnodes_files/__init__.py
funcnodes_files/react_plugin/js/main.js
funcnodes_files/react_plugin/js/main.js.LICENSE.txt
funcnodes_files-1.0.0.dist-info/METADATA
funcnodes_files-1.0.0.dist-info/WHEEL
funcnodes_files-1.0.0.dist-info/entry_points.txt
funcnodes_files-1.0.0.dist-info/licenses/LICENSE
funcnodes_files-1.0.0.dist-info/RECORD
