Metadata-Version: 2.4
Name: funcnodes-files
Version: 1.0.0
Summary: A package for managing file downloads, uploads, and folder handling within FuncNodes workflows.
Project-URL: homepage, https://github.com/Linkdlab/funcnodes_files
Project-URL: source, https://github.com/Linkdlab/funcnodes_files
Project-URL: tracker, https://github.com/Linkdlab/funcnodes_files/issues
Project-URL: download, https://pypi.org/project/funcnodes-files/#files
Author-email: Julian Kimmig <julian.kimmig@linkdlab.de>
License: AGPL-3.0
License-File: LICENSE
Classifier: License :: OSI Approved :: GNU Affero General Public License v3 or later (AGPLv3+)
Requires-Python: >=3.11
Requires-Dist: asynctoolkit>=0.1.3
Requires-Dist: funcnodes-core>=0.3.40
Requires-Dist: funcnodes-react-flow>=1.0.0
Requires-Dist: funcnodes>=0.5.6
Requires-Dist: requests; sys_platform != 'emscripten'
